[
  {
    "$type": "SampleGame.Parts.PhysicalObject, SampleGame",
    "Corporeal": true,
    "Moveable": true,
    "Condition": 10000,
    "DefaultDamageThreshold": 0,
    "DefaultDamageMultiplier": 1.0,
    "EquipmentSlots": 3,
    "Weight": 0.0,
    "Size": "Gnome",
    "WieldableSingleHandSize": "Goliath",
    "Id": 0
  },
  {
    "$type": "SampleGame.Parts.EntityName, SampleGame",
    "ProperName": "",
    "GeneralName": "sword",
    "ObscuredName": null,
    "ShortDescription": "sword",
    "LongDescription": null,
    "Pronoun": null,
    "Id": 0
  },
  {
    "$type": "SampleGame.Parts.Damager, SampleGame",
    "DamageType": "MechanicalSlashing",
    "DamageAmount": 3000,
    "Id": 0
  }
]